{
  "maxConductivity": 3000,
  "appliances": [
    {
      "weight": 0.45,
      "color": "RED",
      "name": "HAIRDRYER",
      "brand": "ROWENTA",
      "powerConsumption": 220,
      "forContinuousWork": false,
      "connectToSocket": false,
      "turnOn": false
    },
    {
      "weight": 3.5,
      "color": "BLACK",
      "name": "VACUUM_CLEANER",
      "brand": "PHILIPS",
      "powerConsumption": 1000,
      "forContinuousWork": false,
      "connectToSocket": false,
      "turnOn": false
    },
    {
      "weight": 15,
      "color": "WHITE",
      "name": "WASHING_MACHINE",
      "brand": "SAMSUNG",
      "powerConsumption": 1700,
      "forContinuousWork": true,
      "connectToSocket": false,
      "turnOn": false
    },
    {
      "weight": 65,
      "color": "WHITE",
      "name": "FRIDGE",
      "brand": "SAMSUNG",
      "powerConsumption": 250,
      "forContinuousWork": true,
      "connectToSocket": false,
      "turnOn": false
    },
    {
      "weight": 0.5,
      "color": "BLUE",
      "name": "LAMP",
      "brand": "MAXUS",
      "powerConsumption": 60,
      "forContinuousWork": true,
      "connectToSocket": false,
      "turnOn": false
    },
    {
      "weight": 2,
      "color": "BLACK",
      "name": "LAPTOP",
      "brand": "ASUS",
      "powerConsumption": 100,
      "forContinuousWork": true,
      "connectToSocket": false,
      "turnOn": false
    },
    {
      "weight": 7,
      "color": "BLACK",
      "name": "TV",
      "brand": "SAMSUNG",
      "powerConsumption": 700,
      "forContinuousWork": true,
      "connectToSocket": false,
      "turnOn": false
    },
    {
      "weight": 0.4,
      "color": "BLACK",
      "name": "IRON",
      "brand": "PHILIPS",
      "powerConsumption": 1000,
      "forContinuousWork": false,
      "connectToSocket": false,
      "turnOn": false
    }
  ]
}
